BuildBinary.py
TheLanguage1/__init__.py
TheLanguage1/Common/Errors.py
TheLanguage1/Common/Location.py
TheLanguage1/Common/Range.py
TheLanguage1/Common/Region.py
TheLanguage1/Common/__init__.py
TheLanguage1-0.2.0.dist-info/LICENSE
TheLanguage1-0.2.0.dist-info/LICENSE.txt
TheLanguage1-0.2.0.dist-info/METADATA
TheLanguage1-0.2.0.dist-info/WHEEL
TheLanguage1-0.2.0.dist-info/top_level.txt
TheLanguage1-0.2.0.dist-info/RECORD
