Metadata-Version: 2.1
Name: TheLanguage1
Version: 0.2.0
Summary: Initial implementation of "TheLanguage".
Author-email: David Brownell <db@DavidBrownell.com>
License: MIT
Project-URL: Homepage, https://github.com/davidbrownell/TheLanguage1
Project-URL: Documentation, https://github.com/davidbrownell/TheLanguage1
Project-URL: Repository, https://github.com/davidbrownell/TheLanguage1
Classifier: License :: OSI Approved :: MIT License
Classifier: Operating System :: MacOS
Classifier: Operating System :: Microsoft :: Windows
Classifier: Operating System :: POSIX :: Linux
Classifier: Programming Language :: Python
Classifier: Programming Language :: Python :: 3.10
Classifier: Programming Language :: Python :: 3.11
Classifier: Programming Language :: Python :: 3.12
License-File: LICENSE
License-File: LICENSE.txt
Requires-Dist: dbrownell-Common
Requires-Dist: typer ~=0.9
Provides-Extra: dev
Requires-Dist: dbrownell-DevTools ; extra == 'dev'
Provides-Extra: package
Requires-Dist: build ==1.* ; extra == 'package'
Requires-Dist: cx-Freeze ==6.* ; extra == 'package'
Requires-Dist: twine ==4.* ; extra == 'package'
